<?xml version="1.0" encoding="utf-8"?>
<Defs>
    <!-- Erin's Wildlife > Animal Collab Project Vanilla-Style -->
    <CherryPicker.DefList MayRequire="owlchemist.cherrypicker, erin.wildlife, acpteam.acpvanillastyle">
        <defName>dupes_erin_wildlife_acpteam_acpvanillastyle</defName>
        <label>Erin's Wildlife &gt; Animal Collab Project Vanilla-Style</label>
        <defs>
            <li MayRequire="erin.wildlife">PawnKindDef/ACPHedgehog</li> <!--ERN_Hedgehog/hedgehog-->
            <li MayRequire="erin.wildlife">PawnKindDef/ACPPtarmigan</li> <!--ERN_ptarmigan/Ptarmigan-->
            <li MayRequire="erin.wildlife">PawnKindDef/ACPRedPanda</li> <!--ERN_Redpanda/Red panda-->
            <li MayRequire="erin.wildlife">ThingDef/ACPHedgehog</li> <!--ERN_Hedgehog/hedgehog-->
            <li MayRequire="erin.wildlife">ThingDef/ACPPtarmigan</li> <!--ERN_ptarmigan/Ptarmigan-->
            <li MayRequire="erin.wildlife">ThingDef/ACPEggPtarmiganFertilized</li> <!--EggPtarmiganFertilized/ptarmigan egg (fert.)-->
            <li MayRequire="erin.wildlife">ThingDef/ACPEggPtarmiganUnfertilized</li> <!--EggPtarmiganUnfertilized/ptarmigan egg (unfert.)-->
            <li MayRequire="erin.wildlife">ThingDef/ACPRedPanda</li> <!--ERN_Redpanda/Red panda-->
        </defs>
    </CherryPicker.DefList>
</Defs>